[{"name":"Bishoujo Mahjong Puzzle (Japan) (Aftermarket) (Unl).zip","myrient_href":"No-Intro/Sega%20-%20Game%20Gear%20%28Aftermarket%29/Bishoujo%20Mahjong%20Puzzle%20%28Japan%29%20%28Aftermarket%29%20%28Unl%29.zip","is_folder":false,"next":null},{"name":"Black Castle (World) (Aftermarket) (Unl).zip","myrient_href":"No-Intro/Sega%20-%20Game%20Gear%20%28Aftermarket%29/Black%20Castle%20%28World%29%20%28Aftermarket%29%20%28Unl%29.zip","is_folder":false,"next":null},{"name":"Black Castle (World) (v1.1) (Aftermarket) (Unl).zip","myrient_href":"No-Intro/Sega%20-%20Game%20Gear%20%28Aftermarket%29/Black%20Castle%20%28World%29%20%28v1.1%29%20%28Aftermarket%29%20%28Unl%29.zip","is_folder":false,"next":null},{"name":"Burger Kitchen (Japan) (Aftermarket) (Unl).zip","myrient_href":"No-Intro/Sega%20-%20Game%20Gear%20%28Aftermarket%29/Burger%20Kitchen%20%28Japan%29%20%28Aftermarket%29%20%28Unl%29.zip","is_folder":false,"next":null},{"name":"Colorlines (World) (Demo) (Aftermarket) (Unl).zip","myrient_href":"No-Intro/Sega%20-%20Game%20Gear%20%28Aftermarket%29/Colorlines%20%28World%29%20%28Demo%29%20%28Aftermarket%29%20%28Unl%29.zip","is_folder":false,"next":null},{"name":"Cross Bomber (World) (v1.0) (Aftermarket) (Unl).zip","myrient_href":"No-Intro/Sega%20-%20Game%20Gear%20%28Aftermarket%29/Cross%20Bomber%20%28World%29%20%28v1.0%29%20%28Aftermarket%29%20%28Unl%29.zip","is_folder":false,"next":null},{"name":"Cross Bomber (World) (v1.1) (Aftermarket) (Unl).zip","myrient_href":"No-Intro/Sega%20-%20Game%20Gear%20%28Aftermarket%29/Cross%20Bomber%20%28World%29%20%28v1.1%29%20%28Aftermarket%29%20%28Unl%29.zip","is_folder":false,"next":null},{"name":"Cross Chase (World) (v1.0) (Aftermarket) (Unl).zip","myrient_href":"No-Intro/Sega%20-%20Game%20Gear%20%28Aftermarket%29/Cross%20Chase%20%28World%29%20%28v1.0%29%20%28Aftermarket%29%20%28Unl%29.zip","is_folder":false,"next":null},{"name":"Cross Chase (World) (v1.1) (Aftermarket) (Unl).zip","myrient_href":"No-Intro/Sega%20-%20Game%20Gear%20%28Aftermarket%29/Cross%20Chase%20%28World%29%20%28v1.1%29%20%28Aftermarket%29%20%28Unl%29.zip","is_folder":false,"next":null},{"name":"Cross Horde (World) (v1.0) (Aftermarket) (Unl).zip","myrient_href":"No-Intro/Sega%20-%20Game%20Gear%20%28Aftermarket%29/Cross%20Horde%20%28World%29%20%28v1.0%29%20%28Aftermarket%29%20%28Unl%29.zip","is_folder":false,"next":null},{"name":"Cross Horde (World) (v1.1) (Aftermarket) (Unl).zip","myrient_href":"No-Intro/Sega%20-%20Game%20Gear%20%28Aftermarket%29/Cross%20Horde%20%28World%29%20%28v1.1%29%20%28Aftermarket%29%20%28Unl%29.zip","is_folder":false,"next":null},{"name":"Cross Shoot (World) (Aftermarket) (Unl).zip","myrient_href":"No-Intro/Sega%20-%20Game%20Gear%20%28Aftermarket%29/Cross%20Shoot%20%28World%29%20%28Aftermarket%29%20%28Unl%29.zip","is_folder":false,"next":null},{"name":"Cross Snake (World) (Aftermarket) (Unl).zip","myrient_href":"No-Intro/Sega%20-%20Game%20Gear%20%28Aftermarket%29/Cross%20Snake%20%28World%29%20%28Aftermarket%29%20%28Unl%29.zip","is_folder":false,"next":null},{"name":"Dangerous Demolition (World) (Aftermarket) (Unl).zip","myrient_href":"No-Intro/Sega%20-%20Game%20Gear%20%28Aftermarket%29/Dangerous%20Demolition%20%28World%29%20%28Aftermarket%29%20%28Unl%29.zip","is_folder":false,"next":null},{"name":"Donkey.GG (World) (Proto) (Aftermarket) (Unl).zip","myrient_href":"No-Intro/Sega%20-%20Game%20Gear%20%28Aftermarket%29/Donkey.GG%20%28World%29%20%28Proto%29%20%28Aftermarket%29%20%28Unl%29.zip","is_folder":false,"next":null},{"name":"Dracula no Shiro (Japan) (Aftermarket) (Unl).zip","myrient_href":"No-Intro/Sega%20-%20Game%20Gear%20%28Aftermarket%29/Dracula%20no%20Shiro%20%28Japan%29%20%28Aftermarket%29%20%28Unl%29.zip","is_folder":false,"next":null},{"name":"Fire Track (World) (Aftermarket) (Unl).zip","myrient_href":"No-Intro/Sega%20-%20Game%20Gear%20%28Aftermarket%29/Fire%20Track%20%28World%29%20%28Aftermarket%29%20%28Unl%29.zip","is_folder":false,"next":null},{"name":"Flying Hamburgers (World) (Aftermarket) (Unl).zip","myrient_href":"No-Intro/Sega%20-%20Game%20Gear%20%28Aftermarket%29/Flying%20Hamburgers%20%28World%29%20%28Aftermarket%29%20%28Unl%29.zip","is_folder":false,"next":null},{"name":"GG Hicolor Demo (World) (v1.00) (Auto Demo) (Aftermarket) (Unl).zip","myrient_href":"No-Intro/Sega%20-%20Game%20Gear%20%28Aftermarket%29/GG%20Hicolor%20Demo%20%28World%29%20%28v1.00%29%20%28Auto%20Demo%29%20%28Aftermarket%29%20%28Unl%29.zip","is_folder":false,"next":null},{"name":"GG Hicolor Demo (World) (v1.01) (Auto Demo) (Aftermarket) (Unl).zip","myrient_href":"No-Intro/Sega%20-%20Game%20Gear%20%28Aftermarket%29/GG%20Hicolor%20Demo%20%28World%29%20%28v1.01%29%20%28Auto%20Demo%29%20%28Aftermarket%29%20%28Unl%29.zip","is_folder":false,"next":null},{"name":"GG Nibbles (World) (v1.0) (Aftermarket) (Unl).zip","myrient_href":"No-Intro/Sega%20-%20Game%20Gear%20%28Aftermarket%29/GG%20Nibbles%20%28World%29%20%28v1.0%29%20%28Aftermarket%29%20%28Unl%29.zip","is_folder":false,"next":null},{"name":"GG Nibbles (World) (v1.1) (Aftermarket) (Unl).zip","myrient_href":"No-Intro/Sega%20-%20Game%20Gear%20%28Aftermarket%29/GG%20Nibbles%20%28World%29%20%28v1.1%29%20%28Aftermarket%29%20%28Unl%29.zip","is_folder":false,"next":null},{"name":"GG Nibbles (World) (v1.2) (Aftermarket) (Unl).zip","myrient_href":"No-Intro/Sega%20-%20Game%20Gear%20%28Aftermarket%29/GG%20Nibbles%20%28World%29%20%28v1.2%29%20%28Aftermarket%29%20%28Unl%29.zip","is_folder":false,"next":null},{"name":"GG Nibbles (World) (v1.3) (Aftermarket) (Unl).zip","myrient_href":"No-Intro/Sega%20-%20Game%20Gear%20%28Aftermarket%29/GG%20Nibbles%20%28World%29%20%28v1.3%29%20%28Aftermarket%29%20%28Unl%29.zip","is_folder":false,"next":null},{"name":"GG Turrican (World) (v0.9) (Demo) (Aftermarket) (Unl).zip","myrient_href":"No-Intro/Sega%20-%20Game%20Gear%20%28Aftermarket%29/GG%20Turrican%20%28World%29%20%28v0.9%29%20%28Demo%29%20%28Aftermarket%29%20%28Unl%29.zip","is_folder":false,"next":null},{"name":"GG Turrican (World) (v1.0) (Demo) (Aftermarket) (Unl).zip","myrient_href":"No-Intro/Sega%20-%20Game%20Gear%20%28Aftermarket%29/GG%20Turrican%20%28World%29%20%28v1.0%29%20%28Demo%29%20%28Aftermarket%29%20%28Unl%29.zip","is_folder":false,"next":null},{"name":"Gamegear Button Test (World) (v0.3.0) (Program) (Aftermarket) (Unl).zip","myrient_href":"No-Intro/Sega%20-%20Game%20Gear%20%28Aftermarket%29/Gamegear%20Button%20Test%20%28World%29%20%28v0.3.0%29%20%28Program%29%20%28Aftermarket%29%20%28Unl%29.zip","is_folder":false,"next":null},{"name":"Gun Stream - Challenge Version (Japan) (En) (Aftermarket) (Unl) [b].zip","myrient_href":"No-Intro/Sega%20-%20Game%20Gear%20%28Aftermarket%29/Gun%20Stream%20-%20Challenge%20Version%20%28Japan%29%20%28En%29%20%28Aftermarket%29%20%28Unl%29%20%5Bb%5D.zip","is_folder":false,"next":null},{"name":"Hamburgers en Route to Switzerland (World) (v0.70) (Proto) (Aftermarket) (Unl).zip","myrient_href":"No-Intro/Sega%20-%20Game%20Gear%20%28Aftermarket%29/Hamburgers%20en%20Route%20to%20Switzerland%20%28World%29%20%28v0.70%29%20%28Proto%29%20%28Aftermarket%29%20%28Unl%29.zip","is_folder":false,"next":null},{"name":"Hamburgers en Route to Switzerland (World) (v0.75) (Proto) (Aftermarket) (Unl).zip","myrient_href":"No-Intro/Sega%20-%20Game%20Gear%20%28Aftermarket%29/Hamburgers%20en%20Route%20to%20Switzerland%20%28World%29%20%28v0.75%29%20%28Proto%29%20%28Aftermarket%29%20%28Unl%29.zip","is_folder":false,"next":null},{"name":"Hamburgers en Route to Switzerland 2 (World) (Aftermarket) (Unl).zip","myrient_href":"No-Intro/Sega%20-%20Game%20Gear%20%28Aftermarket%29/Hamburgers%20en%20Route%20to%20Switzerland%202%20%28World%29%20%28Aftermarket%29%20%28Unl%29.zip","is_folder":false,"next":null},{"name":"Hermano (World) (Aftermarket) (Unl).zip","myrient_href":"No-Intro/Sega%20-%20Game%20Gear%20%28Aftermarket%29/Hermano%20%28World%29%20%28Aftermarket%29%20%28Unl%29.zip","is_folder":false,"next":null},{"name":"Justin Harder Reel (World) (Auto Demo) (Aftermarket) (Unl).zip","myrient_href":"No-Intro/Sega%20-%20Game%20Gear%20%28Aftermarket%29/Justin%20Harder%20Reel%20%28World%29%20%28Auto%20Demo%29%20%28Aftermarket%29%20%28Unl%29.zip","is_folder":false,"next":null},{"name":"Kaiju Feeder (World) (Aftermarket) (Unl).zip","myrient_href":"No-Intro/Sega%20-%20Game%20Gear%20%28Aftermarket%29/Kaiju%20Feeder%20%28World%29%20%28Aftermarket%29%20%28Unl%29.zip","is_folder":false,"next":null},{"name":"Mai Nurse (World) (Aftermarket) (Unl).zip","myrient_href":"No-Intro/Sega%20-%20Game%20Gear%20%28Aftermarket%29/Mai%20Nurse%20%28World%29%20%28Aftermarket%29%20%28Unl%29.zip","is_folder":false,"next":null},{"name":"Mieyen Mini (World) (Aftermarket) (Unl).zip","myrient_href":"No-Intro/Sega%20-%20Game%20Gear%20%28Aftermarket%29/Mieyen%20Mini%20%28World%29%20%28Aftermarket%29%20%28Unl%29.zip","is_folder":false,"next":null},{"name":"Monaco Master (World) (v1.1) (Aftermarket) (Unl).zip","myrient_href":"No-Intro/Sega%20-%20Game%20Gear%20%28Aftermarket%29/Monaco%20Master%20%28World%29%20%28v1.1%29%20%28Aftermarket%29%20%28Unl%29.zip","is_folder":false,"next":null},{"name":"Mr. Ultra (World) (v0.1) (Demo) (Aftermarket) (Unl).zip","myrient_href":"No-Intro/Sega%20-%20Game%20Gear%20%28Aftermarket%29/Mr.%20Ultra%20%28World%29%20%28v0.1%29%20%28Demo%29%20%28Aftermarket%29%20%28Unl%29.zip","is_folder":false,"next":null},{"name":"Mr. Ultra 2 (World) (Aftermarket) (Unl).zip","myrient_href":"No-Intro/Sega%20-%20Game%20Gear%20%28Aftermarket%29/Mr.%20Ultra%202%20%28World%29%20%28Aftermarket%29%20%28Unl%29.zip","is_folder":false,"next":null},{"name":"Mr. Ultra 2 (World) (Beta) (Aftermarket) (Unl).zip","myrient_href":"No-Intro/Sega%20-%20Game%20Gear%20%28Aftermarket%29/Mr.%20Ultra%202%20%28World%29%20%28Beta%29%20%28Aftermarket%29%20%28Unl%29.zip","is_folder":false,"next":null},{"name":"Neko (World) (Demo 1) (Aftermarket) (Unl).zip","myrient_href":"No-Intro/Sega%20-%20Game%20Gear%20%28Aftermarket%29/Neko%20%28World%29%20%28Demo%201%29%20%28Aftermarket%29%20%28Unl%29.zip","is_folder":false,"next":null},{"name":"Neko (World) (Demo 2) (Aftermarket) (Unl).zip","myrient_href":"No-Intro/Sega%20-%20Game%20Gear%20%28Aftermarket%29/Neko%20%28World%29%20%28Demo%202%29%20%28Aftermarket%29%20%28Unl%29.zip","is_folder":false,"next":null},{"name":"Pac-Man (World) (Aftermarket) (Unl).zip","myrient_href":"No-Intro/Sega%20-%20Game%20Gear%20%28Aftermarket%29/Pac-Man%20%28World%29%20%28Aftermarket%29%20%28Unl%29.zip","is_folder":false,"next":null},{"name":"Petris (World) (v1.1) (Proto) (Aftermarket) (Unl).zip","myrient_href":"No-Intro/Sega%20-%20Game%20Gear%20%28Aftermarket%29/Petris%20%28World%29%20%28v1.1%29%20%28Proto%29%20%28Aftermarket%29%20%28Unl%29.zip","is_folder":false,"next":null},{"name":"Polka Sheep (World) (Aftermarket) (Unl).zip","myrient_href":"No-Intro/Sega%20-%20Game%20Gear%20%28Aftermarket%29/Polka%20Sheep%20%28World%29%20%28Aftermarket%29%20%28Unl%29.zip","is_folder":false,"next":null},{"name":"Princess Gardening (Japan) (Aftermarket) (Unl).zip","myrient_href":"No-Intro/Sega%20-%20Game%20Gear%20%28Aftermarket%29/Princess%20Gardening%20%28Japan%29%20%28Aftermarket%29%20%28Unl%29.zip","is_folder":false,"next":null},{"name":"Quest (World) (Demo) (Aftermarket) (Unl).zip","myrient_href":"No-Intro/Sega%20-%20Game%20Gear%20%28Aftermarket%29/Quest%20%28World%29%20%28Demo%29%20%28Aftermarket%29%20%28Unl%29.zip","is_folder":false,"next":null},{"name":"Road Toad (World) (v0.19) (Proto) (Aftermarket) (Unl).zip","myrient_href":"No-Intro/Sega%20-%20Game%20Gear%20%28Aftermarket%29/Road%20Toad%20%28World%29%20%28v0.19%29%20%28Proto%29%20%28Aftermarket%29%20%28Unl%29.zip","is_folder":false,"next":null},{"name":"Shuriken (World) (Aftermarket) (Unl).zip","myrient_href":"No-Intro/Sega%20-%20Game%20Gear%20%28Aftermarket%29/Shuriken%20%28World%29%20%28Aftermarket%29%20%28Unl%29.zip","is_folder":false,"next":null},{"name":"Stinger (World) (Aftermarket) (Unl).zip","myrient_href":"No-Intro/Sega%20-%20Game%20Gear%20%28Aftermarket%29/Stinger%20%28World%29%20%28Aftermarket%29%20%28Unl%29.zip","is_folder":false,"next":null},{"name":"Super Princess' 2092 - Exodus (World) (Aftermarket) (Unl).zip","myrient_href":"No-Intro/Sega%20-%20Game%20Gear%20%28Aftermarket%29/Super%20Princess%27%202092%20-%20Exodus%20%28World%29%20%28Aftermarket%29%20%28Unl%29.zip","is_folder":false,"next":null},{"name":"Super Princess' 2092 - Exodus (World) (v1.1) (Aftermarket) (Unl).zip","myrient_href":"No-Intro/Sega%20-%20Game%20Gear%20%28Aftermarket%29/Super%20Princess%27%202092%20-%20Exodus%20%28World%29%20%28v1.1%29%20%28Aftermarket%29%20%28Unl%29.zip","is_folder":false,"next":null},{"name":"Sushi Nights (World) (Aftermarket) (Unl).zip","myrient_href":"No-Intro/Sega%20-%20Game%20Gear%20%28Aftermarket%29/Sushi%20Nights%20%28World%29%20%28Aftermarket%29%20%28Unl%29.zip","is_folder":false,"next":null},{"name":"Sushi Nights (World) (v1.01) (Aftermarket) (Unl).zip","myrient_href":"No-Intro/Sega%20-%20Game%20Gear%20%28Aftermarket%29/Sushi%20Nights%20%28World%29%20%28v1.01%29%20%28Aftermarket%29%20%28Unl%29.zip","is_folder":false,"next":null},{"name":"Sushi Nights (World) (v1.04) (Aftermarket) (Unl).zip","myrient_href":"No-Intro/Sega%20-%20Game%20Gear%20%28Aftermarket%29/Sushi%20Nights%20%28World%29%20%28v1.04%29%20%28Aftermarket%29%20%28Unl%29.zip","is_folder":false,"next":null},{"name":"Swabby (World) (v1.11) (Aftermarket) (Unl).zip","myrient_href":"No-Intro/Sega%20-%20Game%20Gear%20%28Aftermarket%29/Swabby%20%28World%29%20%28v1.11%29%20%28Aftermarket%29%20%28Unl%29.zip","is_folder":false,"next":null},{"name":"Sword of Stone, The (World) (Demo) (Aftermarket) (Unl).zip","myrient_href":"No-Intro/Sega%20-%20Game%20Gear%20%28Aftermarket%29/Sword%20of%20Stone%2C%20The%20%28World%29%20%28Demo%29%20%28Aftermarket%29%20%28Unl%29.zip","is_folder":false,"next":null},{"name":"Tetris4GG (World) (v0.9) (Aftermarket) (Unl).zip","myrient_href":"No-Intro/Sega%20-%20Game%20Gear%20%28Aftermarket%29/Tetris4GG%20%28World%29%20%28v0.9%29%20%28Aftermarket%29%20%28Unl%29.zip","is_folder":false,"next":null},{"name":"Trex (World) (Proto) (Aftermarket) (Unl).zip","myrient_href":"No-Intro/Sega%20-%20Game%20Gear%20%28Aftermarket%29/Trex%20%28World%29%20%28Proto%29%20%28Aftermarket%29%20%28Unl%29.zip","is_folder":false,"next":null},{"name":"Vexed (World) (v1.15) (Aftermarket) (Unl).zip","myrient_href":"No-Intro/Sega%20-%20Game%20Gear%20%28Aftermarket%29/Vexed%20%28World%29%20%28v1.15%29%20%28Aftermarket%29%20%28Unl%29.zip","is_folder":false,"next":null},{"name":"Waternet (World) (Aftermarket) (Unl).zip","myrient_href":"No-Intro/Sega%20-%20Game%20Gear%20%28Aftermarket%29/Waternet%20%28World%29%20%28Aftermarket%29%20%28Unl%29.zip","is_folder":false,"next":null},{"name":"Windows GG (World) (Program) (Aftermarket) (Unl).zip","myrient_href":"No-Intro/Sega%20-%20Game%20Gear%20%28Aftermarket%29/Windows%20GG%20%28World%29%20%28Program%29%20%28Aftermarket%29%20%28Unl%29.zip","is_folder":false,"next":null},{"name":"Wing Warriors (World) (En,Fr,Es) (v1.0) (Aftermarket) (Unl).zip","myrient_href":"No-Intro/Sega%20-%20Game%20Gear%20%28Aftermarket%29/Wing%20Warriors%20%28World%29%20%28En%2CFr%2CEs%29%20%28v1.0%29%20%28Aftermarket%29%20%28Unl%29.zip","is_folder":false,"next":null},{"name":"Wing Warriors (World) (En,Fr,Es) (v1.1) (Aftermarket) (Unl).zip","myrient_href":"No-Intro/Sega%20-%20Game%20Gear%20%28Aftermarket%29/Wing%20Warriors%20%28World%29%20%28En%2CFr%2CEs%29%20%28v1.1%29%20%28Aftermarket%29%20%28Unl%29.zip","is_folder":false,"next":null},{"name":"Wolfenstein (World) (v1.16) (Aftermarket) (Unl).zip","myrient_href":"No-Intro/Sega%20-%20Game%20Gear%20%28Aftermarket%29/Wolfenstein%20%28World%29%20%28v1.16%29%20%28Aftermarket%29%20%28Unl%29.zip","is_folder":false,"next":null},{"name":"Yakitori Meijin Torigin (Japan) (Aftermarket) (Unl).zip","myrient_href":"No-Intro/Sega%20-%20Game%20Gear%20%28Aftermarket%29/Yakitori%20Meijin%20Torigin%20%28Japan%29%20%28Aftermarket%29%20%28Unl%29.zip","is_folder":false,"next":null},{"name":"Yum! (World) (v0.33) (Proto) (Aftermarket) (Unl).zip","myrient_href":"No-Intro/Sega%20-%20Game%20Gear%20%28Aftermarket%29/Yum%21%20%28World%29%20%28v0.33%29%20%28Proto%29%20%28Aftermarket%29%20%28Unl%29.zip","is_folder":false,"next":null},{"name":"Zoop'em Up (World) (Aftermarket) (Unl).zip","myrient_href":"No-Intro/Sega%20-%20Game%20Gear%20%28Aftermarket%29/Zoop%27em%20Up%20%28World%29%20%28Aftermarket%29%20%28Unl%29.zip","is_folder":false,"next":null}]